README.txt
bootstrap.py
buildout.cfg
setup.cfg
setup.py
docs/HISTORY.txt
docs/INSTALL.txt
docs/LICENSE.GPL
docs/LICENSE.txt
src/collective/__init__.py
src/collective.fourohfour.egg-info/PKG-INFO
src/collective.fourohfour.egg-info/SOURCES.txt
src/collective.fourohfour.egg-info/dependency_links.txt
src/collective.fourohfour.egg-info/entry_points.txt
src/collective.fourohfour.egg-info/namespace_packages.txt
src/collective.fourohfour.egg-info/not-zip-safe
src/collective.fourohfour.egg-info/requires.txt
src/collective.fourohfour.egg-info/top_level.txt
src/collective/fourohfour/__init__.py
src/collective/fourohfour/browser.py
src/collective/fourohfour/configure.zcml
src/collective/fourohfour/interfaces.py
src/collective/fourohfour/middleware.py
src/collective/fourohfour/browser_templates/fourohfour.pt
src/collective/fourohfour/profiles/default/browserlayer.xml
src/collective/fourohfour/profiles/default/metadata.xml
src/collective/fourohfour/profiles/default/registry.xml
src/collective/fourohfour/tests/__init__.py
src/collective/fourohfour/tests/layer.py
src/collective/fourohfour/tests/test_middleware.py
src/collective/fourohfour/tests/test_setup.py