Metadata-Version: 1.0
Name: collective.fourohfour
Version: 1.0a5
Summary: Aliasing of Plone content
Home-page: http://pypi.python.org/pypi/collective.fourohfour
Author: Martin Aspeli
Author-email: optilude@gmail.com
License: GPL
Keywords: plone fourohfour
Platform: UNKNOWN
Classifier: Framework :: Plone
Classifier: Programming Language :: Python
Classifier: Topic :: Software Development :: Libraries :: Python Modules
